[
    {
        "category_name": "Garages",
        "image_path": "assets/Icons/garage.png"
    },
    {
        "category_name": "Service centers",
        "image_path": "assets/Icons/service_center.png"
    },
    {
        "category_name": "Spare parts/accessories",
        "image_path": "assets/Icons/spare_parts.png"
    },
    {
        "category_name": "Parkings",
        "image_path": "assets/Icons/parking.png"
    },
    {
        "category_name": "Emergency vehicles",
        "image_path": "assets/Icons/emergency.png"
    },
    {
        "category_name": "Vehicle Modifications",
        "image_path": "assets/Icons/modification.png"
    },
    {
        "category_name": "Tire services & shops",
        "image_path": "assets/Icons/tyre.png"
    },
    {
        "category_name": "Hiring vehicles",
        "image_path": "assets/Icons/hire.png"
    },
    {
        "category_name": "Renting vehicles",
        "image_path": "assets/Icons/rent.png"
    }
]